pyansystools/__init__.py
pyansystools/geo2d.py
pyansystools/inline.py
pyansystools/macros.py
pyansystools/material.py
pyansystools/material_db.py
pyansystools/ramberg_osgood.py
tests/__init__.py
tests/conftest.py
tests/test_geo2d.py
tests/test_inline.py
tests/test_material.py
tests/test_material_db.py
tests/test_tools.py
tests/testcases.py
pyansystools-0.0.5.dist-info/LICENSE
pyansystools-0.0.5.dist-info/METADATA
pyansystools-0.0.5.dist-info/WHEEL
pyansystools-0.0.5.dist-info/top_level.txt
pyansystools-0.0.5.dist-info/RECORD
