Metadata-Version: 2.1
Name: pyansystools
Version: 0.0.5
Summary: Provides classes to simplify the work with ANSYS using the python module ansys-mapdl-core.
Home-page: https://github.com/natter1/pyansystools
Author: Nathanael Jöhrmann
Author-email: 
License: MIT
Classifier: Development Status :: 3 - Alpha
Classifier: License :: OSI Approved :: MIT License
Classifier: Programming Language :: Python :: 3.9
Classifier: Programming Language :: Python :: 3.10
Requires-Python: >=3.9
License-File: LICENSE
